__init__.py
pyHiM.py
core/__init__.py
core/dask_cluster.py
core/data_file.py
core/data_manager.py
core/function_caller.py
core/parameters.py
core/pyhim_logging.py
core/run_args.py
core/saving.py
imageProcessing/__init__.py
imageProcessing/alignImages.py
imageProcessing/alignImages3D.py
imageProcessing/imageProcessing.py
imageProcessing/localization_table.py
imageProcessing/localize_2d.py
imageProcessing/localize_3d.py
imageProcessing/makeProjections.py
imageProcessing/mask_2d.py
imageProcessing/mask_3d.py
imageProcessing/register_local.py
imageProcessing/segmentMasks.py
imageProcessing/segmentMasks3D.py
imageProcessing/segmentSources3D.py
matrixOperations/HIMmatrixOperations.py
matrixOperations/__init__.py
matrixOperations/build_matrix.py
matrixOperations/build_traces.py
matrixOperations/chromatin_trace_table.py
matrixOperations/filter_localizations.py
matrixOperations/register_localizations.py
plots/__init__.py
plots/figureCompare2Matrices.py
plots/figureHiMmatrix.py
plots/figureN_HiMmatrices.py
plots/figureSingleCell.py
plots/plot_3way.py
plots/plot_4M.py
plots/plot_bootstrapping.py
plots/plotting_functions.py
postProcessing/__init__.py
postProcessing/analyze_localizations.py
postProcessing/compare_PWD_matrices.py
postProcessing/localization_merge.py
postProcessing/mask_cellpose.py
postProcessing/mask_manual.py
postProcessing/npy_to_tiff.py
postProcessing/processHiMmatrix.py
postProcessing/pwd_matrix_2_pdb.py
postProcessing/trace_analyzer.py
postProcessing/trace_assign_mask.py
postProcessing/trace_combinator.py
postProcessing/trace_correct_coordinates.py
postProcessing/trace_export_to_fofct.py
postProcessing/trace_filter.py
postProcessing/trace_filter_advanced.py
postProcessing/trace_import_from_fofct.py
postProcessing/trace_impute_genomic_coordinates.py
postProcessing/trace_merge.py
postProcessing/trace_pearsons.py
postProcessing/trace_plot.py
postProcessing/trace_splitter.py
postProcessing/trace_stats.py
postProcessing/trace_to_matrix.py
pyhim-0.10.0.dist-info/licenses/LICENSE
pyhim-0.10.0.dist-info/METADATA
pyhim-0.10.0.dist-info/WHEEL
pyhim-0.10.0.dist-info/entry_points.txt
pyhim-0.10.0.dist-info/top_level.txt
pyhim-0.10.0.dist-info/RECORD
