Metadata-Version: 2.4
Name: pyhim
Version: 0.10.0
Summary: Pipeline and functions to analyse multiplexed DNA-FISH data
Author-email: Marcelo Nollmann <marcelo.nollmann@cbs.cnrs.fr>
License:                    GNU LESSER GENERAL PUBLIC LICENSE
Project-URL: Homepage, https://github.com/marcnol/pyHiM
Keywords: astropy,csbdeep,dask,matplotlib,numpy,numba,photutils,roipoly,scikit-learn,scikit-image,stardist,pympler,tqdm,scipy,tifffile
Requires-Python: >=3.9
License-File: LICENSE
Requires-Dist: apifish>=0.6.4.dev0
Requires-Dist: dataclasses-json
Requires-Dist: astropy>=4.3.1
Requires-Dist: csbdeep>=0.6.3
Requires-Dist: dask[distributed]>=2023.4.1
Requires-Dist: matplotlib==3.5.1
Requires-Dist: numba>=0.54.1
Requires-Dist: numpy>=1.19.5
Requires-Dist: photutils>=1.1.0
Requires-Dist: pympler>=1.0.1
Requires-Dist: roipoly>=0.5.3
Requires-Dist: scikit-image==0.19.2
Requires-Dist: scikit-learn>=1.1.1
Requires-Dist: scipy>=1.10.3
Requires-Dist: stardist>=0.7.3
Requires-Dist: tifffile>=2021.10.10
Requires-Dist: tqdm>=4.63.0
Dynamic: license-file
